{
  "stats": {
    "suites": 4,
    "tests": 39,
    "passes": 39,
    "pending": 0,
    "failures": 0,
    "start": "2023-09-08T05:38:22.176Z",
    "end": "2023-09-08T05:43:34.635Z",
    "duration": 281243,
    "testsRegistered": 39,
    "passPercent": 100,
    "pendingPercent": 0,
    "other": 0,
    "hasOther": false,
    "skipped": 0,
    "hasSkipped": false
  },
  "results": [
    {
      "uuid": "e1e96d06-8272-4c94-b2f2-80bf152b47bd",
      "title": "",
      "fullFile": "cypress\\e2e\\unlimited-training\\employee\\profile.cy.ts",
      "file": "cypress\\e2e\\unlimited-training\\employee\\profile.cy.ts",
      "beforeHooks": [],
      "afterHooks": [],
      "tests": [],
      "suites": [
        {
          "uuid": "10858ffd-4b6b-4806-8a95-51931b06a171",
          "title": "UT : Employee : General",
          "fullFile": "",
          "file": "",
          "beforeHooks": [],
          "afterHooks": [],
          "tests": [
            {
              "title": "Application Menu : Default items should visible",
              "fullTitle": "UT : Employee : General Application Menu : Default items should visible",
              "timedOut": null,
              "duration": 30154,
              "state": "passed",
              "speed": "slow",
              "pass": true,
              "fail": false,
              "pending": false,
              "context": null,
              "code": "cy.loginPortal();\nSIDE_NAV_BAR.basePoint();\nSIDE_NAV_BAR.verifyItemsIfExist('E');",
              "err": {},
              "uuid": "7497c7a8-04da-4517-958f-d92be0953ed6",
              "parentUUID": "10858ffd-4b6b-4806-8a95-51931b06a171",
              "isHook": false,
              "skipped": false
            },
            {
              "title": "Application Menu : Check texts/labels if visible",
              "fullTitle": "UT : Employee : General Application Menu : Check texts/labels if visible",
              "timedOut": null,
              "duration": 14,
              "state": "passed",
              "speed": "fast",
              "pass": true,
              "fail": false,
              "pending": false,
              "context": null,
              "code": "SIDE_NAV_BAR.verifyTextsIfContains('E');",
              "err": {},
              "uuid": "de941f48-3d53-47cc-a263-7673e6089df3",
              "parentUUID": "10858ffd-4b6b-4806-8a95-51931b06a171",
              "isHook": false,
              "skipped": false
            },
            {
              "title": "My Profile : Default items and fields should visible",
              "fullTitle": "UT : Employee : General My Profile : Default items and fields should visible",
              "timedOut": null,
              "duration": 1942,
              "state": "passed",
              "speed": "fast",
              "pass": true,
              "fail": false,
              "pending": false,
              "context": null,
              "code": "SIDE_NAV_BAR.editProfile();\nMY_PROFILE.verifyItemsIfExist('UT', 'E');\nFOOTER.verifyItemsIfExist('UT');\nHEADER.verifyItemsIfExist('E');",
              "err": {},
              "uuid": "635fda88-3a84-4311-b291-0828fdafaad4",
              "parentUUID": "10858ffd-4b6b-4806-8a95-51931b06a171",
              "isHook": false,
              "skipped": false
            },
            {
              "title": "My Profile : Check texts/labels if visible",
              "fullTitle": "UT : Employee : General My Profile : Check texts/labels if visible",
              "timedOut": null,
              "duration": 99,
              "state": "passed",
              "speed": "fast",
              "pass": true,
              "fail": false,
              "pending": false,
              "context": null,
              "code": "MY_PROFILE.verifyTextsIfContains('UT', 'E');\nFOOTER.verifyTextsIfContains('', 'UT');\nHEADER.verifyTextsIfContains();",
              "err": {},
              "uuid": "07a9d410-ac3f-465e-be94-65b5acf37a27",
              "parentUUID": "10858ffd-4b6b-4806-8a95-51931b06a171",
              "isHook": false,
              "skipped": false
            },
            {
              "title": "My Profile : Update Basic Information",
              "fullTitle": "UT : Employee : General My Profile : Update Basic Information",
              "timedOut": null,
              "duration": 14434,
              "state": "passed",
              "speed": "slow",
              "pass": true,
              "fail": false,
              "pending": false,
              "context": null,
              "code": "MY_PROFILE.profile('update_basic_info', 'UT');\nCOMM_ELEMENTS.toaster('success');\ncy.reload();",
              "err": {},
              "uuid": "0d11f4c0-dd33-4455-9b5a-ad77db9a74d0",
              "parentUUID": "10858ffd-4b6b-4806-8a95-51931b06a171",
              "isHook": false,
              "skipped": false
            },
            {
              "title": "My Profile (NEGATIVE) : Invalidate Update button with empty mandatory fields",
              "fullTitle": "UT : Employee : General My Profile (NEGATIVE) : Invalidate Update button with empty mandatory fields",
              "timedOut": null,
              "duration": 3985,
              "state": "passed",
              "speed": "fast",
              "pass": true,
              "fail": false,
              "pending": false,
              "context": null,
              "code": "MY_PROFILE.profile('clear_all_fields', '');",
              "err": {},
              "uuid": "eda844aa-4930-4545-b265-859c4752517b",
              "parentUUID": "10858ffd-4b6b-4806-8a95-51931b06a171",
              "isHook": false,
              "skipped": false
            },
            {
              "title": "My Profile (NEGATIVE) : Password and verify fields password does not match",
              "fullTitle": "UT : Employee : General My Profile (NEGATIVE) : Password and verify fields password does not match",
              "timedOut": null,
              "duration": 2192,
              "state": "passed",
              "speed": "fast",
              "pass": true,
              "fail": false,
              "pending": false,
              "context": null,
              "code": "MY_PROFILE.profile('un_matched_password', '');\ncy.reload();",
              "err": {},
              "uuid": "1b660306-0a0b-4ac0-ae6c-9ba973ae67c2",
              "parentUUID": "10858ffd-4b6b-4806-8a95-51931b06a171",
              "isHook": false,
              "skipped": false
            },
            {
              "title": "My Profile (EDGE CASE) : Add alphabet and special character on phone number",
              "fullTitle": "UT : Employee : General My Profile (EDGE CASE) : Add alphabet and special character on phone number",
              "timedOut": null,
              "duration": 3418,
              "state": "passed",
              "speed": "fast",
              "pass": true,
              "fail": false,
              "pending": false,
              "context": null,
              "code": "MY_PROFILE.profile('validate_phone_number', '');",
              "err": {},
              "uuid": "b8f150ee-5fce-4c86-b003-755984a92792",
              "parentUUID": "10858ffd-4b6b-4806-8a95-51931b06a171",
              "isHook": false,
              "skipped": false
            },
            {
              "title": "My Profile (EDGE CASE) : Add alphabet and special character on mobile number",
              "fullTitle": "UT : Employee : General My Profile (EDGE CASE) : Add alphabet and special character on mobile number",
              "timedOut": null,
              "duration": 356,
              "state": "passed",
              "speed": "fast",
              "pass": true,
              "fail": false,
              "pending": false,
              "context": null,
              "code": "MY_PROFILE.profile('validate_mobile_number', '');",
              "err": {},
              "uuid": "a772c23f-fcc4-4659-bb0a-d8deefc72edc",
              "parentUUID": "10858ffd-4b6b-4806-8a95-51931b06a171",
              "isHook": false,
              "skipped": false
            },
            {
              "title": "My Profile (OOTB) : Able to change country code on phone number",
              "fullTitle": "UT : Employee : General My Profile (OOTB) : Able to change country code on phone number",
              "timedOut": null,
              "duration": 714,
              "state": "passed",
              "speed": "fast",
              "pass": true,
              "fail": false,
              "pending": false,
              "context": null,
              "code": "MY_PROFILE.profile('validate_mobile_country_code', '');",
              "err": {},
              "uuid": "55da616a-f876-481a-a3bc-6f23d9f28183",
              "parentUUID": "10858ffd-4b6b-4806-8a95-51931b06a171",
              "isHook": false,
              "skipped": false
            },
            {
              "title": "My Profile (OOTB) : Disable update button when mandatory fields are empty",
              "fullTitle": "UT : Employee : General My Profile (OOTB) : Disable update button when mandatory fields are empty",
              "timedOut": null,
              "duration": 789,
              "state": "passed",
              "speed": "fast",
              "pass": true,
              "fail": false,
              "pending": false,
              "context": null,
              "code": "MY_PROFILE.profile('disable_update_button', '');",
              "err": {},
              "uuid": "d00bbd3c-a516-4975-8e55-b1931a814921",
              "parentUUID": "10858ffd-4b6b-4806-8a95-51931b06a171",
              "isHook": false,
              "skipped": false
            },
            {
              "title": "My Profile : Validate Password Strength - risk",
              "fullTitle": "UT : Employee : General My Profile : Validate Password Strength - risk",
              "timedOut": null,
              "duration": 424,
              "state": "passed",
              "speed": "fast",
              "pass": true,
              "fail": false,
              "pending": false,
              "context": null,
              "code": "COMM_ELEMENTS.passwordStrength('risky');",
              "err": {},
              "uuid": "34d27c38-f043-4dbc-80f4-c881749e1034",
              "parentUUID": "10858ffd-4b6b-4806-8a95-51931b06a171",
              "isHook": false,
              "skipped": false
            },
            {
              "title": "My Profile : Validate Password Strength - weak",
              "fullTitle": "UT : Employee : General My Profile : Validate Password Strength - weak",
              "timedOut": null,
              "duration": 319,
              "state": "passed",
              "speed": "fast",
              "pass": true,
              "fail": false,
              "pending": false,
              "context": null,
              "code": "COMM_ELEMENTS.passwordStrength('weak');",
              "err": {},
              "uuid": "65300501-6979-487b-bbf2-ad1d15a4cbf3",
              "parentUUID": "10858ffd-4b6b-4806-8a95-51931b06a171",
              "isHook": false,
              "skipped": false
            },
            {
              "title": "My Profile : Validate Password Strength - fair",
              "fullTitle": "UT : Employee : General My Profile : Validate Password Strength - fair",
              "timedOut": null,
              "duration": 410,
              "state": "passed",
              "speed": "fast",
              "pass": true,
              "fail": false,
              "pending": false,
              "context": null,
              "code": "COMM_ELEMENTS.passwordStrength('fair');",
              "err": {},
              "uuid": "ac5ee7d1-2d68-412a-bd5b-c9ad9a1061b2",
              "parentUUID": "10858ffd-4b6b-4806-8a95-51931b06a171",
              "isHook": false,
              "skipped": false
            },
            {
              "title": "My Profile : Validate Password Strength - good",
              "fullTitle": "UT : Employee : General My Profile : Validate Password Strength - good",
              "timedOut": null,
              "duration": 437,
              "state": "passed",
              "speed": "fast",
              "pass": true,
              "fail": false,
              "pending": false,
              "context": null,
              "code": "COMM_ELEMENTS.passwordStrength('good');",
              "err": {},
              "uuid": "c963bcb1-4a6f-4584-9f9c-cf9a26ecb774",
              "parentUUID": "10858ffd-4b6b-4806-8a95-51931b06a171",
              "isHook": false,
              "skipped": false
            },
            {
              "title": "My Profile : Validate Password Strength - strong",
              "fullTitle": "UT : Employee : General My Profile : Validate Password Strength - strong",
              "timedOut": null,
              "duration": 565,
              "state": "passed",
              "speed": "fast",
              "pass": true,
              "fail": false,
              "pending": false,
              "context": null,
              "code": "COMM_ELEMENTS.passwordStrength('strong');",
              "err": {},
              "uuid": "b1d4b5cb-1102-4d38-9aad-16cadb2e1c2a",
              "parentUUID": "10858ffd-4b6b-4806-8a95-51931b06a171",
              "isHook": false,
              "skipped": false
            }
          ],
          "suites": [],
          "passes": [
            "7497c7a8-04da-4517-958f-d92be0953ed6",
            "de941f48-3d53-47cc-a263-7673e6089df3",
            "635fda88-3a84-4311-b291-0828fdafaad4",
            "07a9d410-ac3f-465e-be94-65b5acf37a27",
            "0d11f4c0-dd33-4455-9b5a-ad77db9a74d0",
            "eda844aa-4930-4545-b265-859c4752517b",
            "1b660306-0a0b-4ac0-ae6c-9ba973ae67c2",
            "b8f150ee-5fce-4c86-b003-755984a92792",
            "a772c23f-fcc4-4659-bb0a-d8deefc72edc",
            "55da616a-f876-481a-a3bc-6f23d9f28183",
            "d00bbd3c-a516-4975-8e55-b1931a814921",
            "34d27c38-f043-4dbc-80f4-c881749e1034",
            "65300501-6979-487b-bbf2-ad1d15a4cbf3",
            "ac5ee7d1-2d68-412a-bd5b-c9ad9a1061b2",
            "c963bcb1-4a6f-4584-9f9c-cf9a26ecb774",
            "b1d4b5cb-1102-4d38-9aad-16cadb2e1c2a"
          ],
          "failures": [],
          "pending": [],
          "skipped": [],
          "duration": 60252,
          "root": false,
          "rootEmpty": false,
          "_timeout": 2000
        }
      ],
      "passes": [],
      "failures": [],
      "pending": [],
      "skipped": [],
      "duration": 0,
      "root": true,
      "rootEmpty": true,
      "_timeout": 2000
    },
    {
      "uuid": "9095044a-c646-4a4d-8973-234f800c3b89",
      "title": "",
      "fullFile": "cypress\\e2e\\unlimited-training\\employee\\reg_codes.cy.ts",
      "file": "cypress\\e2e\\unlimited-training\\employee\\reg_codes.cy.ts",
      "beforeHooks": [],
      "afterHooks": [],
      "tests": [],
      "suites": [
        {
          "uuid": "ec61206f-8b90-42b3-af2b-c882e8f19504",
          "title": "UT : Add New Managers : Registration codes",
          "fullFile": "",
          "file": "",
          "beforeHooks": [],
          "afterHooks": [],
          "tests": [
            {
              "title": "Default items should visible",
              "fullTitle": "UT : Add New Managers : Registration codes Default items should visible",
              "timedOut": null,
              "duration": 3056,
              "state": "passed",
              "speed": "fast",
              "pass": true,
              "fail": false,
              "pending": false,
              "context": null,
              "code": "NEW_USER.register('default_items', null);",
              "err": {},
              "uuid": "121de02c-8a36-4127-99bb-0800e2233914",
              "parentUUID": "ec61206f-8b90-42b3-af2b-c882e8f19504",
              "isHook": false,
              "skipped": false
            },
            {
              "title": "Validate successful new user account creation",
              "fullTitle": "UT : Add New Managers : Registration codes Validate successful new user account creation",
              "timedOut": null,
              "duration": 7908,
              "state": "passed",
              "speed": "medium",
              "pass": true,
              "fail": false,
              "pending": false,
              "context": null,
              "code": "NEW_USER.register('add_user', 'success_creation');",
              "err": {},
              "uuid": "c2ae36da-18d5-4ee4-8054-123c04867d10",
              "parentUUID": "ec61206f-8b90-42b3-af2b-c882e8f19504",
              "isHook": false,
              "skipped": false
            },
            {
              "title": "Validate existing user",
              "fullTitle": "UT : Add New Managers : Registration codes Validate existing user",
              "timedOut": null,
              "duration": 6197,
              "state": "passed",
              "speed": "medium",
              "pass": true,
              "fail": false,
              "pending": false,
              "context": null,
              "code": "NEW_USER.register('add_user', 'already_exist');",
              "err": {},
              "uuid": "df7cd8a1-a073-4436-ae53-f7681665d01d",
              "parentUUID": "ec61206f-8b90-42b3-af2b-c882e8f19504",
              "isHook": false,
              "skipped": false
            },
            {
              "title": "Validate cancel adding new user",
              "fullTitle": "UT : Add New Managers : Registration codes Validate cancel adding new user",
              "timedOut": null,
              "duration": 275,
              "state": "passed",
              "speed": "fast",
              "pass": true,
              "fail": false,
              "pending": false,
              "context": null,
              "code": "cy.visit(Cypress.env(\"url\"));\nNEW_USER.register('cancel_creating_user', null);",
              "err": {},
              "uuid": "eec497a1-3311-4240-9685-076c8d2cb58e",
              "parentUUID": "ec61206f-8b90-42b3-af2b-c882e8f19504",
              "isHook": false,
              "skipped": false
            },
            {
              "title": "Check field validations",
              "fullTitle": "UT : Add New Managers : Registration codes Check field validations",
              "timedOut": null,
              "duration": 1841,
              "state": "passed",
              "speed": "fast",
              "pass": true,
              "fail": false,
              "pending": false,
              "context": null,
              "code": "NEW_USER.register('disable_submit_button', null);",
              "err": {},
              "uuid": "b1860c2f-1e81-4872-b126-9c2386579ced",
              "parentUUID": "ec61206f-8b90-42b3-af2b-c882e8f19504",
              "isHook": false,
              "skipped": false
            },
            {
              "title": "Validate matching email and confirm email fields",
              "fullTitle": "UT : Add New Managers : Registration codes Validate matching email and confirm email fields",
              "timedOut": null,
              "duration": 5410,
              "state": "passed",
              "speed": "medium",
              "pass": true,
              "fail": false,
              "pending": false,
              "context": null,
              "code": "NEW_USER.register('validation_fields', 'email_not_matched');",
              "err": {},
              "uuid": "e3815979-654d-4196-bab5-62dcfdefc366",
              "parentUUID": "ec61206f-8b90-42b3-af2b-c882e8f19504",
              "isHook": false,
              "skipped": false
            },
            {
              "title": "Validate matching password and verify password fields",
              "fullTitle": "UT : Add New Managers : Registration codes Validate matching password and verify password fields",
              "timedOut": null,
              "duration": 4541,
              "state": "passed",
              "speed": "fast",
              "pass": true,
              "fail": false,
              "pending": false,
              "context": null,
              "code": "cy.visit(Cypress.env(\"url\"));\nNEW_USER.register('validation_fields', 'passwords_not_matched');",
              "err": {},
              "uuid": "2c698a77-ebb9-465b-bfc0-5864b2558f1e",
              "parentUUID": "ec61206f-8b90-42b3-af2b-c882e8f19504",
              "isHook": false,
              "skipped": false
            },
            {
              "title": "Create account : Validate Password Strength - risk",
              "fullTitle": "UT : Add New Managers : Registration codes Create account : Validate Password Strength - risk",
              "timedOut": null,
              "duration": 465,
              "state": "passed",
              "speed": "fast",
              "pass": true,
              "fail": false,
              "pending": false,
              "context": null,
              "code": "NEW_USER.newUser.click();\nCOMM_ELEMENTS.passwordStrength('risky');",
              "err": {},
              "uuid": "8b1be476-e296-48d6-9a1b-397165c8da18",
              "parentUUID": "ec61206f-8b90-42b3-af2b-c882e8f19504",
              "isHook": false,
              "skipped": false
            },
            {
              "title": "Create account : Validate Password Strength - weak",
              "fullTitle": "UT : Add New Managers : Registration codes Create account : Validate Password Strength - weak",
              "timedOut": null,
              "duration": 501,
              "state": "passed",
              "speed": "fast",
              "pass": true,
              "fail": false,
              "pending": false,
              "context": null,
              "code": "NEW_USER.newUser.click();\nCOMM_ELEMENTS.passwordStrength('weak');",
              "err": {},
              "uuid": "813a126b-6090-4b6a-912e-446eafb0d409",
              "parentUUID": "ec61206f-8b90-42b3-af2b-c882e8f19504",
              "isHook": false,
              "skipped": false
            },
            {
              "title": "Create account : Validate Password Strength - fair",
              "fullTitle": "UT : Add New Managers : Registration codes Create account : Validate Password Strength - fair",
              "timedOut": null,
              "duration": 580,
              "state": "passed",
              "speed": "fast",
              "pass": true,
              "fail": false,
              "pending": false,
              "context": null,
              "code": "cy.visit(Cypress.env(\"url\"));\nNEW_USER.newUser.click();\nCOMM_ELEMENTS.passwordStrength('fair');",
              "err": {},
              "uuid": "3d0ef58b-1deb-440f-8562-984b0d0346e8",
              "parentUUID": "ec61206f-8b90-42b3-af2b-c882e8f19504",
              "isHook": false,
              "skipped": false
            },
            {
              "title": "Create account : Validate Password Strength - good",
              "fullTitle": "UT : Add New Managers : Registration codes Create account : Validate Password Strength - good",
              "timedOut": null,
              "duration": 566,
              "state": "passed",
              "speed": "fast",
              "pass": true,
              "fail": false,
              "pending": false,
              "context": null,
              "code": "NEW_USER.newUser.click();\nCOMM_ELEMENTS.passwordStrength('good');",
              "err": {},
              "uuid": "4a59855a-3a2e-410b-8a71-6f9d3a2a5945",
              "parentUUID": "ec61206f-8b90-42b3-af2b-c882e8f19504",
              "isHook": false,
              "skipped": false
            },
            {
              "title": "Create account : Validate Password Strength - strong",
              "fullTitle": "UT : Add New Managers : Registration codes Create account : Validate Password Strength - strong",
              "timedOut": null,
              "duration": 668,
              "state": "passed",
              "speed": "fast",
              "pass": true,
              "fail": false,
              "pending": false,
              "context": null,
              "code": "NEW_USER.newUser.click();\nCOMM_ELEMENTS.passwordStrength('strong');",
              "err": {},
              "uuid": "6a63e9b7-344e-4715-b02c-ef1b5e459bf9",
              "parentUUID": "ec61206f-8b90-42b3-af2b-c882e8f19504",
              "isHook": false,
              "skipped": false
            }
          ],
          "suites": [],
          "passes": [
            "121de02c-8a36-4127-99bb-0800e2233914",
            "c2ae36da-18d5-4ee4-8054-123c04867d10",
            "df7cd8a1-a073-4436-ae53-f7681665d01d",
            "eec497a1-3311-4240-9685-076c8d2cb58e",
            "b1860c2f-1e81-4872-b126-9c2386579ced",
            "e3815979-654d-4196-bab5-62dcfdefc366",
            "2c698a77-ebb9-465b-bfc0-5864b2558f1e",
            "8b1be476-e296-48d6-9a1b-397165c8da18",
            "813a126b-6090-4b6a-912e-446eafb0d409",
            "3d0ef58b-1deb-440f-8562-984b0d0346e8",
            "4a59855a-3a2e-410b-8a71-6f9d3a2a5945",
            "6a63e9b7-344e-4715-b02c-ef1b5e459bf9"
          ],
          "failures": [],
          "pending": [],
          "skipped": [],
          "duration": 32008,
          "root": false,
          "rootEmpty": false,
          "_timeout": 2000
        }
      ],
      "passes": [],
      "failures": [],
      "pending": [],
      "skipped": [],
      "duration": 0,
      "root": true,
      "rootEmpty": true,
      "_timeout": 2000
    },
    {
      "uuid": "abf4e796-f8ce-4fad-9a5b-31d826ce489e",
      "title": "",
      "fullFile": "cypress\\e2e\\unlimited-training\\employee\\my-dashboard\\employee_training.cy.ts",
      "file": "cypress\\e2e\\unlimited-training\\employee\\my-dashboard\\employee_training.cy.ts",
      "beforeHooks": [],
      "afterHooks": [],
      "tests": [],
      "suites": [
        {
          "uuid": "9b799c12-0127-455d-9a4a-4a08f133defa",
          "title": "UT : Employee : Dashboard : Training",
          "fullFile": "",
          "file": "",
          "beforeHooks": [],
          "afterHooks": [],
          "tests": [
            {
              "title": "Default items should visible",
              "fullTitle": "UT : Employee : Dashboard : Training Default items should visible",
              "timedOut": null,
              "duration": 26848,
              "state": "passed",
              "speed": "slow",
              "pass": true,
              "fail": false,
              "pending": false,
              "context": null,
              "code": "TRAINING.validateScenario('default_items', 'UT', 'E');\nFOOTER.verifyItemsIfExist('UT');\nHEADER.verifyItemsIfExist('E');",
              "err": {},
              "uuid": "72738ba9-81d0-40ed-bf18-9a979c500cbf",
              "parentUUID": "9b799c12-0127-455d-9a4a-4a08f133defa",
              "isHook": false,
              "skipped": false
            },
            {
              "title": "Check texts/labels if visible",
              "fullTitle": "UT : Employee : Dashboard : Training Check texts/labels if visible",
              "timedOut": null,
              "duration": 739,
              "state": "passed",
              "speed": "fast",
              "pass": true,
              "fail": false,
              "pending": false,
              "context": null,
              "code": "TRAINING.viewTrainingTab();\nTRAINING.validateScenario('default_texts', 'UT', 'E');\nFOOTER.verifyItemsIfExist('UT');\nHEADER.verifyItemsIfExist('E');",
              "err": {},
              "uuid": "a734fca5-d09c-4390-88ea-4e61cb035c25",
              "parentUUID": "9b799c12-0127-455d-9a4a-4a08f133defa",
              "isHook": false,
              "skipped": false
            },
            {
              "title": "Validate Cybersecurity Training Videos",
              "fullTitle": "UT : Employee : Dashboard : Training Validate Cybersecurity Training Videos",
              "timedOut": null,
              "duration": 25385,
              "state": "passed",
              "speed": "slow",
              "pass": true,
              "fail": false,
              "pending": false,
              "context": null,
              "code": "TRAINING.validateScenario('security_training_videos', 'UT', null);",
              "err": {},
              "uuid": "5df10860-59c4-4e18-ae11-a5472d1dc773",
              "parentUUID": "9b799c12-0127-455d-9a4a-4a08f133defa",
              "isHook": false,
              "skipped": false
            },
            {
              "title": "Training (EDGE) : Validate Security Quiz",
              "fullTitle": "UT : Employee : Dashboard : Training Training (EDGE) : Validate Security Quiz",
              "timedOut": null,
              "duration": 73082,
              "state": "passed",
              "speed": "slow",
              "pass": true,
              "fail": false,
              "pending": false,
              "context": null,
              "code": "TRAINING.validateScenario('complete_security_quiz', 'UT', null);\nCOMM_ELEMENTS.hideLoadingScreen();",
              "err": {},
              "uuid": "8e2c8d08-ef18-4b62-bd8e-3a6986c7ec63",
              "parentUUID": "9b799c12-0127-455d-9a4a-4a08f133defa",
              "isHook": false,
              "skipped": false
            },
            {
              "title": "Training (EDGE) : Validate Reviewing Security Quiz",
              "fullTitle": "UT : Employee : Dashboard : Training Training (EDGE) : Validate Reviewing Security Quiz",
              "timedOut": null,
              "duration": 3935,
              "state": "passed",
              "speed": "fast",
              "pass": true,
              "fail": false,
              "pending": false,
              "context": null,
              "code": "TRAINING.validateScenario('review_security_quiz', 'UT', null);\nCOMM_ELEMENTS.hideLoadingScreen();",
              "err": {},
              "uuid": "7cc45aca-f5f9-4c67-b7d3-d7dbe374a623",
              "parentUUID": "9b799c12-0127-455d-9a4a-4a08f133defa",
              "isHook": false,
              "skipped": false
            },
            {
              "title": "Training : Validate Retaking Security Quiz",
              "fullTitle": "UT : Employee : Dashboard : Training Training : Validate Retaking Security Quiz",
              "timedOut": null,
              "duration": 7986,
              "state": "passed",
              "speed": "medium",
              "pass": true,
              "fail": false,
              "pending": false,
              "context": null,
              "code": "TRAINING.validateScenario('retake_security_quiz', 'UT', null);\nCOMM_ELEMENTS.hideLoadingScreen();",
              "err": {},
              "uuid": "e2209b35-d7f6-4d3b-8665-0cd36e434551",
              "parentUUID": "9b799c12-0127-455d-9a4a-4a08f133defa",
              "isHook": false,
              "skipped": false
            },
            {
              "title": "Training : Validate Step 3 - Print Your Certificate",
              "fullTitle": "UT : Employee : Dashboard : Training Training : Validate Step 3 - Print Your Certificate",
              "timedOut": null,
              "duration": 6989,
              "state": "passed",
              "speed": "medium",
              "pass": true,
              "fail": false,
              "pending": false,
              "context": null,
              "code": "TRAINING.validateScenario('print_certificate', 'UT', null);\nCOMM_ELEMENTS.hideLoadingScreen();",
              "err": {},
              "uuid": "963dff9a-281c-46c6-969f-f3047e18da67",
              "parentUUID": "9b799c12-0127-455d-9a4a-4a08f133defa",
              "isHook": false,
              "skipped": false
            }
          ],
          "suites": [],
          "passes": [
            "72738ba9-81d0-40ed-bf18-9a979c500cbf",
            "a734fca5-d09c-4390-88ea-4e61cb035c25",
            "5df10860-59c4-4e18-ae11-a5472d1dc773",
            "8e2c8d08-ef18-4b62-bd8e-3a6986c7ec63",
            "7cc45aca-f5f9-4c67-b7d3-d7dbe374a623",
            "e2209b35-d7f6-4d3b-8665-0cd36e434551",
            "963dff9a-281c-46c6-969f-f3047e18da67"
          ],
          "failures": [],
          "pending": [],
          "skipped": [],
          "duration": 144964,
          "root": false,
          "rootEmpty": false,
          "_timeout": 2000
        }
      ],
      "passes": [],
      "failures": [],
      "pending": [],
      "skipped": [],
      "duration": 0,
      "root": true,
      "rootEmpty": true,
      "_timeout": 2000
    },
    {
      "uuid": "94905da2-5985-41d7-b330-8b980805d612",
      "title": "",
      "fullFile": "cypress\\e2e\\unlimited-training\\employee\\contact_us.cy.ts",
      "file": "cypress\\e2e\\unlimited-training\\employee\\contact_us.cy.ts",
      "beforeHooks": [],
      "afterHooks": [],
      "tests": [],
      "suites": [
        {
          "uuid": "7f89846e-2ae8-4a6c-b9dc-a12ef7efe9d4",
          "title": "UT : Employee : Contact Us",
          "fullFile": "",
          "file": "",
          "beforeHooks": [],
          "afterHooks": [],
          "tests": [
            {
              "title": "Default items should visible",
              "fullTitle": "UT : Employee : Contact Us Default items should visible",
              "timedOut": null,
              "duration": 28531,
              "state": "passed",
              "speed": "slow",
              "pass": true,
              "fail": false,
              "pending": false,
              "context": null,
              "code": "CONTACT_US.verifyItemsIfExist();\nFOOTER.verifyItemsIfExist('UT');\nHEADER.verifyItemsIfExist('E');",
              "err": {},
              "uuid": "3570d892-e033-40f6-9f96-82521e6af742",
              "parentUUID": "7f89846e-2ae8-4a6c-b9dc-a12ef7efe9d4",
              "isHook": false,
              "skipped": false
            },
            {
              "title": "Check texts/labels if visible",
              "fullTitle": "UT : Employee : Contact Us Check texts/labels if visible",
              "timedOut": null,
              "duration": 2301,
              "state": "passed",
              "speed": "fast",
              "pass": true,
              "fail": false,
              "pending": false,
              "context": null,
              "code": "CONTACT_US.verifyTextsIfContains();\nFOOTER.verifyTextsIfContains('', 'UT');\nHEADER.verifyTextsIfContains();",
              "err": {},
              "uuid": "12410c88-fb2b-4898-81cb-9443d77b6a9f",
              "parentUUID": "7f89846e-2ae8-4a6c-b9dc-a12ef7efe9d4",
              "isHook": false,
              "skipped": false
            },
            {
              "title": "Validate Cancel submission",
              "fullTitle": "UT : Employee : Contact Us Validate Cancel submission",
              "timedOut": null,
              "duration": 3747,
              "state": "passed",
              "speed": "fast",
              "pass": true,
              "fail": false,
              "pending": false,
              "context": null,
              "code": "CONTACT_US.cancelSubmission();",
              "err": {},
              "uuid": "05392217-049a-4013-a1a4-72c4f842a95e",
              "parentUUID": "7f89846e-2ae8-4a6c-b9dc-a12ef7efe9d4",
              "isHook": false,
              "skipped": false
            },
            {
              "title": "Validate contact-us submission",
              "fullTitle": "UT : Employee : Contact Us Validate contact-us submission",
              "timedOut": null,
              "duration": 9440,
              "state": "passed",
              "speed": "medium",
              "pass": true,
              "fail": false,
              "pending": false,
              "context": null,
              "code": "SIDE_NAV_BAR.editProfile();\nCONTACT_US.viewContactUsTab();\nCONTACT_US.submitContactUs();",
              "err": {},
              "uuid": "0a16c281-3abe-4c57-b2df-6df4d551a7e9",
              "parentUUID": "7f89846e-2ae8-4a6c-b9dc-a12ef7efe9d4",
              "isHook": false,
              "skipped": false
            }
          ],
          "suites": [],
          "passes": [
            "3570d892-e033-40f6-9f96-82521e6af742",
            "12410c88-fb2b-4898-81cb-9443d77b6a9f",
            "05392217-049a-4013-a1a4-72c4f842a95e",
            "0a16c281-3abe-4c57-b2df-6df4d551a7e9"
          ],
          "failures": [],
          "pending": [],
          "skipped": [],
          "duration": 44019,
          "root": false,
          "rootEmpty": false,
          "_timeout": 2000
        }
      ],
      "passes": [],
      "failures": [],
      "pending": [],
      "skipped": [],
      "duration": 0,
      "root": true,
      "rootEmpty": true,
      "_timeout": 2000
    }
  ],
  "meta": {
    "mocha": {
      "version": "7.0.1"
    },
    "mochawesome": {
      "options": {
        "quiet": false,
        "reportFilename": "mochawesome",
        "saveHtml": false,
        "saveJson": true,
        "consoleReporter": "spec",
        "useInlineDiffs": false,
        "code": true
      },
      "version": "7.1.3"
    },
    "marge": {
      "options": {
        "id": "default",
        "reportDir": "cypress/reports/mocha",
        "quite": true,
        "overwrite": false,
        "html": false,
        "json": true
      },
      "version": "6.2.0"
    }
  }
}